assembled/__init__.py
assembled/benchmaker.py
assembled/ensemble_evaluation.py
assembled/metatask.py
assembled/compatibility/__init__.py
assembled/compatibility/faked_classifier.py
assembled/utils/__init__.py
assembled/utils/data_mgmt.py
assembled/utils/isolation.py
assembled/utils/logger.py
assembled/utils/preprocessing.py
assembledopenml/__init__.py
assembledopenml/metaflow.py
assembledopenml/openml_assembler.py
assembledopenml/util/__init__.py
assembledopenml/util/common.py
assembledopenml/util/data_fetching.py
assembled-0.0.4.dist-info/LICENSE
assembled-0.0.4.dist-info/METADATA
assembled-0.0.4.dist-info/WHEEL
assembled-0.0.4.dist-info/top_level.txt
assembled-0.0.4.dist-info/RECORD
