Metadata-Version: 2.1
Name: assembled
Version: 0.0.4
Summary: Efficiently Benchmarking Ensembles in AutoML
Author-email: Lennart Purucker <lennart.purucker@uni-siegen.de>
Project-URL: Homepage, https://github.com/ISG-Siegen/assembled
Project-URL: Bug Tracker, https://github.com/ISG-Siegen/assembled/issues
Classifier: Programming Language :: Python :: 3
Classifier: License :: OSI Approved :: MIT License
Classifier: Operating System :: OS Independent
Requires-Python: >=3.8
License-File: LICENSE
Requires-Dist: numpy (~=1.22.3)
Requires-Dist: pandas (~=1.4.1)
Requires-Dist: scikit-learn (~=1.0.2)
Requires-Dist: scipy (~=1.8.0)
Requires-Dist: tables (~=3.7.0)
Provides-Extra: dev
Requires-Dist: pre-commit (==2.15.0) ; extra == 'dev'
Requires-Dist: pytest (==6.2.5) ; extra == 'dev'
Requires-Dist: Sphinx (==6.1.3) ; extra == 'dev'
Requires-Dist: sphinx-material (==0.0.35) ; extra == 'dev'
Requires-Dist: sphinx-autobuild (==2021.3.14) ; extra == 'dev'
Requires-Dist: sphinx-copybutton (==0.5.1) ; extra == 'dev'
Requires-Dist: sphinx-toolbox (==3.4.0) ; extra == 'dev'
Requires-Dist: sphinx-autodoc-typehints (==1.22) ; extra == 'dev'
Requires-Dist: sphinx-codeautolink (==0.14.1) ; extra == 'dev'
Requires-Dist: build ; extra == 'dev'
Provides-Extra: openml
Requires-Dist: openml (~=0.12.2) ; extra == 'openml'
Requires-Dist: requests (~=2.27.1) ; extra == 'openml'
